ChengxuyuanDeZiwoXiuyangLeohui/README.md
ChengxuyuanDeZiwoXiuyangLeohui/__init__.py
ChengxuyuanDeZiwoXiuyangLeohui/__main__.py
ChengxuyuanDeZiwoXiuyangLeohui/file.epub
ChengxuyuanDeZiwoXiuyangLeohui/index.html
ChengxuyuanDeZiwoXiuyangLeohui/css/__init__.py
ChengxuyuanDeZiwoXiuyangLeohui/css/annotations.css
ChengxuyuanDeZiwoXiuyangLeohui/css/main.css
ChengxuyuanDeZiwoXiuyangLeohui/css/normalize.css
ChengxuyuanDeZiwoXiuyangLeohui/css/popup.css
ChengxuyuanDeZiwoXiuyangLeohui/font/__init__.py
ChengxuyuanDeZiwoXiuyangLeohui/font/fontello.eot
ChengxuyuanDeZiwoXiuyangLeohui/font/fontello.svg
ChengxuyuanDeZiwoXiuyangLeohui/font/fontello.ttf
ChengxuyuanDeZiwoXiuyangLeohui/font/fontello.woff
ChengxuyuanDeZiwoXiuyangLeohui/img/__init__.py
ChengxuyuanDeZiwoXiuyangLeohui/img/annotator-glyph-sprite.png
ChengxuyuanDeZiwoXiuyangLeohui/img/annotator-icon-sprite.png
ChengxuyuanDeZiwoXiuyangLeohui/img/apple-touch-icon.png
ChengxuyuanDeZiwoXiuyangLeohui/img/cancelfullscreen.png
ChengxuyuanDeZiwoXiuyangLeohui/img/close.png
ChengxuyuanDeZiwoXiuyangLeohui/img/fullscreen.png
ChengxuyuanDeZiwoXiuyangLeohui/img/loader.gif
ChengxuyuanDeZiwoXiuyangLeohui/img/menu-icon.png
ChengxuyuanDeZiwoXiuyangLeohui/img/save.png
ChengxuyuanDeZiwoXiuyangLeohui/img/saved.png
ChengxuyuanDeZiwoXiuyangLeohui/img/settings-s.png
ChengxuyuanDeZiwoXiuyangLeohui/img/settings.png
ChengxuyuanDeZiwoXiuyangLeohui/img/star.png
ChengxuyuanDeZiwoXiuyangLeohui/js/__init__.py
ChengxuyuanDeZiwoXiuyangLeohui/js/epub.js
ChengxuyuanDeZiwoXiuyangLeohui/js/epub.min.js
ChengxuyuanDeZiwoXiuyangLeohui/js/epub.min.map
ChengxuyuanDeZiwoXiuyangLeohui/js/hooks.min.js
ChengxuyuanDeZiwoXiuyangLeohui/js/hooks.min.map
ChengxuyuanDeZiwoXiuyangLeohui/js/reader.js
ChengxuyuanDeZiwoXiuyangLeohui/js/reader.js.map
ChengxuyuanDeZiwoXiuyangLeohui/js/reader.min.js
ChengxuyuanDeZiwoXiuyangLeohui/js/reader.min.map
ChengxuyuanDeZiwoXiuyangLeohui/js/hooks/__init__.py
ChengxuyuanDeZiwoXiuyangLeohui/js/hooks/extensions/__init__.py
chengxuyuan_de_ziwo_xiuyang_leohui-2024.3.4.0.dist-info/METADATA
chengxuyuan_de_ziwo_xiuyang_leohui-2024.3.4.0.dist-info/WHEEL
chengxuyuan_de_ziwo_xiuyang_leohui-2024.3.4.0.dist-info/entry_points.txt
chengxuyuan_de_ziwo_xiuyang_leohui-2024.3.4.0.dist-info/top_level.txt
chengxuyuan_de_ziwo_xiuyang_leohui-2024.3.4.0.dist-info/RECORD
